georaptor.py
georaptor-3.0.0.dist-info/LICENSE
georaptor-3.0.0.dist-info/METADATA
georaptor-3.0.0.dist-info/WHEEL
georaptor-3.0.0.dist-info/entry_points.txt
georaptor-3.0.0.dist-info/top_level.txt
georaptor-3.0.0.dist-info/RECORD
