Metadata-Version: 2.1
Name: georaptor
Version: 3.0.0
Summary: A Python Geohash Compression Tool
Home-page: https://github.com/ashwin711/georaptor
Download-URL: https://github.com/ashwin711/georaptor/tarball/3.0.0
Author: Ashwin Nair
Author-email: ashwinnair.ua@gmail.com
License: MIT
Keywords: geohash,optimizer,compression,location
Classifier: Development Status :: 5 - Production/Stable
Classifier: Environment :: Console
Classifier: Intended Audience :: Developers
Classifier: License :: OSI Approved :: Apache Software License
Classifier: Programming Language :: Python
Classifier: Topic :: Software Development :: Libraries :: Python Modules
Classifier: Topic :: Utilities
License-File: LICENSE
Requires-Dist: clint
Requires-Dist: argparse
